harmonica/__init__.py
harmonica/_euler_deconvolution.py
harmonica/_gravity_corrections.py
harmonica/_isostasy.py
harmonica/_transformations.py
harmonica/_utils.py
harmonica/_version.py
harmonica/constants.py
harmonica/_equivalent_sources/__init__.py
harmonica/_equivalent_sources/cartesian.py
harmonica/_equivalent_sources/gradient_boosted.py
harmonica/_equivalent_sources/spherical.py
harmonica/_equivalent_sources/utils.py
harmonica/_forward/__init__.py
harmonica/_forward/_tesseroid_utils.py
harmonica/_forward/_tesseroid_variable_density.py
harmonica/_forward/dipole.py
harmonica/_forward/point.py
harmonica/_forward/prism_gravity.py
harmonica/_forward/prism_layer.py
harmonica/_forward/prism_magnetic.py
harmonica/_forward/tesseroid.py
harmonica/_forward/tesseroid_layer.py
harmonica/_forward/utils.py
harmonica/_io/__init__.py
harmonica/_io/icgem_gdf.py
harmonica/_io/oasis_montaj_grd.py
harmonica/_spherical_harmonics/legendre.py
harmonica/filters/__init__.py
harmonica/filters/_fft.py
harmonica/filters/_filters.py
harmonica/filters/_utils.py
harmonica/tests/__init__.py
harmonica/tests/test_dipole.py
harmonica/tests/test_eq_sources_cartesian.py
harmonica/tests/test_eq_sources_spherical.py
harmonica/tests/test_eq_sources_utils.py
harmonica/tests/test_euler_deconvolution.py
harmonica/tests/test_filters.py
harmonica/tests/test_forward_utils.py
harmonica/tests/test_gradient_boosted_eqs.py
harmonica/tests/test_gravity_corrections.py
harmonica/tests/test_icgem.py
harmonica/tests/test_isostasy.py
harmonica/tests/test_legendre.py
harmonica/tests/test_oasis.py
harmonica/tests/test_point_gravity.py
harmonica/tests/test_prism.py
harmonica/tests/test_prism_layer.py
harmonica/tests/test_prism_magnetic.py
harmonica/tests/test_tesseroid.py
harmonica/tests/test_tesseroid_layer.py
harmonica/tests/test_tesseroid_variable_density.py
harmonica/tests/test_transformations.py
harmonica/tests/test_utils.py
harmonica/tests/test_visualizations.py
harmonica/tests/utils.py
harmonica-0.7.0.dist-info/AUTHORS.md
harmonica-0.7.0.dist-info/LICENSE.txt
harmonica-0.7.0.dist-info/METADATA
harmonica-0.7.0.dist-info/WHEEL
harmonica-0.7.0.dist-info/top_level.txt
harmonica-0.7.0.dist-info/RECORD
