Metadata-Version: 2.1
Name: harmonica
Version: 0.7.0
Summary: Forward modeling, inversion, and processing gravity and magnetic data
Author-email: The Harmonica Developers <fatiandoaterra@protonmail.com>
Maintainer-email: Santiago Soler <santisoler@fastmail.com>
License: BSD-3-Clause
Project-URL: Documentation, https://www.fatiando.org/harmonica
Project-URL: Changelog, https://www.fatiando.org/harmonica/latest/changes.html
Project-URL: Bug Tracker, https://github.com/fatiando/harmonica/issues
Project-URL: Source Code, https://github.com/fatiando/harmonica
Keywords: geoscience,geophysics
Classifier: Development Status :: 5 - Production/Stable
Classifier: Intended Audience :: Science/Research
Classifier: Intended Audience :: Developers
Classifier: Intended Audience :: Education
Classifier: License :: OSI Approved :: BSD License
Classifier: Natural Language :: English
Classifier: Operating System :: OS Independent
Classifier: Topic :: Scientific/Engineering
Classifier: Topic :: Software Development :: Libraries
Classifier: Programming Language :: Python :: 3 :: Only
Classifier: Programming Language :: Python :: 3.9
Classifier: Programming Language :: Python :: 3.10
Classifier: Programming Language :: Python :: 3.11
Classifier: Programming Language :: Python :: 3.12
Requires-Python: >=3.9
License-File: LICENSE.txt
License-File: AUTHORS.md
Requires-Dist: numpy>=1.23
Requires-Dist: pandas>=1.4
Requires-Dist: scipy>=1.9
Requires-Dist: scikit-learn>=1.0
Requires-Dist: numba>=0.53
Requires-Dist: xarray>=2022.03
Requires-Dist: verde>=1.8.1
Requires-Dist: xrft>=1.0
Requires-Dist: choclo>=0.1
Provides-Extra: numba_progress
Requires-Dist: numba-progress; extra == "numba-progress"
Provides-Extra: visualizations
Requires-Dist: pyvista>=0.27; extra == "visualizations"
Requires-Dist: vtk>=9; extra == "visualizations"
